keyhole/__init__.py
keyhole/__main__.py
keyhole/cli.py
keyhole/mosaick/__init__.py
keyhole/mosaick/cli.py
keyhole/mosaick/mosaick.py
keyhole/platforms.py
keyhole/register/__init__.py
keyhole/register/cli.py
keyhole/register/coregister.py
keyhole/register/phase_cross_correlation.py
keyhole-0.2.1.dist-info/entry_points.txt
keyhole-0.2.1.dist-info/WHEEL
keyhole-0.2.1.dist-info/METADATA
keyhole-0.2.1.dist-info/RECORD
