Metadata-Version: 2.1
Name: keyhole
Version: 0.2.1
Summary: Work with declassified keyhole satellite images.
Author: Seth Warn
Author-email: swarn@uark.edu
Requires-Python: >=3.9,<3.10
Classifier: Programming Language :: Python :: 3
Classifier: Programming Language :: Python :: 3.9
Requires-Dist: numpy (>=1.20,<2.0)
Requires-Dist: pyvips (>=2.1.15,<3.0.0)
Requires-Dist: scikit-image (>=0.18,<0.19)
Requires-Dist: scipy (>=1.7,<2.0)
Requires-Dist: tqdm (>=4.62.0,<5.0.0)
